LICENSE.txt
README.rst
corfu.py
pyproject.toml
setup.cfg
setup.py
corfu.egg-info/PKG-INFO
corfu.egg-info/SOURCES.txt
corfu.egg-info/dependency_links.txt
corfu.egg-info/requires.txt
corfu.egg-info/top_level.txt