Metadata-Version: 2.1
Name: corfu
Version: 0.1.1
Summary: projected angular correlation functions
Home-page: https://github.com/ntessore/corfu
Author: Nicolas Tessore
Author-email: n.tessore@ucl.ac.uk
License: MIT
Platform: UNKNOWN
Classifier: Programming Language :: Python :: 3
Classifier: License :: OSI Approved :: MIT License
Classifier: Operating System :: OS Independent
Requires-Python: >=3.6
Provides-Extra: docs
